budget/__init__.py
budget/admin.py
budget/apps.py
budget/common_text.py
budget/models.py
budget/urls.py
budget/filters/__init__.py
budget/filters/filter_budget.py
budget/filters/filter_line_item.py
budget/filters/filter_transaction.py
budget/migrations/0001_initial.py
budget/migrations/__init__.py
budget/serializers/__init__.py
budget/serializers/serializer_budget.py
budget/serializers/serializer_line_item.py
budget/serializers/serializer_transaction.py
budget/views/__init__.py
budget/views/view_budget.py
budget/views/view_line_item.py
budget/views/view_transaction.py
django_budget_backend-0.2.2.dist-info/LICENSE.txt
django_budget_backend-0.2.2.dist-info/METADATA
django_budget_backend-0.2.2.dist-info/WHEEL
django_budget_backend-0.2.2.dist-info/top_level.txt
django_budget_backend-0.2.2.dist-info/RECORD
